{
  "rising": [],
  "newEntries": [
    {
      "id": "775737172",
      "title": "iA Writer",
      "developer": "Information Architects AG",
      "platform": "ios",
      "url": "https://apps.apple.com/us/app/ia-writer/id775737172?uo=4",
      "category": "PRODUCTIVITY",
      "collection": "TOP_PAID",
      "country": "us",
      "todayRank": 31,
      "todayScore": 4.55405,
      "todayReviews": 1480,
      "nicheScore": 95,
      "change": "NEW",
      "recently_featured": false
    },
    {
      "id": "com.viraldevelopment.calai",
      "title": "Cal AI - Food Calorie Tracker",
      "developer": "Improvement Tech LLC",
      "platform": "android",
      "url": "https://play.google.com/store/apps/details?id=com.viraldevelopment.calai",
      "category": "HEALTH_AND_FITNESS",
      "collection": "TOP_GROSSING",
      "country": "us",
      "todayRank": 31,
      "todayScore": 4.6663694,
      "todayReviews": 1477,
      "nicheScore": 100,
      "change": "NEW",
      "recently_featured": true,
      "last_featured_date": "2026-04-07",
      "feature_count": 4
    },
    {
      "id": "6748968935",
      "title": "Payout: Claim Class Actions",
      "developer": "PAYOUT LLC",
      "platform": "ios",
      "url": "https://apps.apple.com/us/app/payout-claim-class-actions/id6748968935?uo=4",
      "category": "FINANCE",
      "collection": "TOP_GROSSING",
      "country": "us",
      "todayRank": 33,
      "todayScore": 4.57822,
      "todayReviews": 4282,
      "nicheScore": 85,
      "change": "NEW",
      "recently_featured": false
    },
    {
      "id": "1201419241",
      "title": "Bullet Journal Companion",
      "developer": "Lightcage LLC",
      "platform": "ios",
      "url": "https://apps.apple.com/us/app/bullet-journal-companion/id1201419241?uo=4",
      "category": "PRODUCTIVITY",
      "collection": "TOP_PAID",
      "country": "us",
      "todayRank": 40,
      "todayScore": 4.50331,
      "todayReviews": 1963,
      "nicheScore": 95,
      "change": "NEW",
      "recently_featured": true,
      "last_featured_date": "2026-04-09",
      "feature_count": 7
    },
    {
      "id": "686378579",
      "title": "Contacts Sync Pro",
      "developer": "Playa Apps",
      "platform": "ios",
      "url": "https://apps.apple.com/us/app/contacts-sync-pro/id686378579?uo=4",
      "category": "PRODUCTIVITY",
      "collection": "TOP_PAID",
      "country": "us",
      "todayRank": 42,
      "todayScore": 4.71139,
      "todayReviews": 790,
      "nicheScore": 95,
      "change": "NEW",
      "recently_featured": false
    },
    {
      "id": "1037668281",
      "title": "CNC Machinist Calculator Pro",
      "developer": "Shane Anderson",
      "platform": "ios",
      "url": "https://apps.apple.com/us/app/cnc-machinist-calculator-pro/id1037668281?uo=4",
      "category": "PRODUCTIVITY",
      "collection": "TOP_PAID",
      "country": "us",
      "todayRank": 44,
      "todayScore": 4.71342,
      "todayReviews": 663,
      "nicheScore": 95,
      "change": "NEW",
      "recently_featured": false
    },
    {
      "id": "com.alphabet.step.luckygo",
      "title": "LuckySteps",
      "developer": "Alphabet Developers LLP",
      "platform": "android",
      "url": "https://play.google.com/store/apps/details?id=com.alphabet.step.luckygo",
      "category": "HEALTH_AND_FITNESS",
      "collection": "TOP_FREE",
      "country": "us",
      "todayRank": 49,
      "todayScore": 4.838565,
      "todayReviews": 524,
      "nicheScore": 95,
      "change": "NEW",
      "recently_featured": true,
      "last_featured_date": "2026-04-07",
      "feature_count": 1
    }
  ],
  "consistent": [
    {
      "id": "415038787",
      "title": "Photo Measures",
      "developer": "Cubent",
      "platform": "ios",
      "url": "https://apps.apple.com/us/app/photo-measures/id415038787?uo=4",
      "category": "PRODUCTIVITY",
      "collection": "TOP_PAID",
      "country": "us",
      "todayRank": 32,
      "todayScore": 4.57308,
      "todayReviews": 520,
      "nicheScore": 95,
      "yesterdayRank": 36,
      "rankChange": 4,
      "streak": 3,
      "totalRise": 13,
      "recently_featured": false
    }
  ],
  "falling": [],
  "summary": {
    "total_tracked": 245,
    "rising_count": 0,
    "new_entries_count": 7,
    "consistent_count": 1,
    "falling_count": 0
  }
}